DTTP/__init__.py
DTTP/net.py
DTTP-0.0.3.dist-info/LICENSE
DTTP-0.0.3.dist-info/METADATA
DTTP-0.0.3.dist-info/WHEEL
DTTP-0.0.3.dist-info/top_level.txt
DTTP-0.0.3.dist-info/RECORD
