Metadata-Version: 2.1
Name: DTTP
Version: 0.0.3
Summary: discord token tool
Home-page: UNKNOWN
Author: zearadiscord
Author-email: UNKNOWN
License: MIT
Platform: UNKNOWN
